Metadata-Version: 1.0
Name: rnd-probability
Version: 0.1
Summary: Gaussian distributions and Binomial distribution
Home-page: UNKNOWN
Author: UNKNOWN
Author-email: UNKNOWN
License: UNKNOWN
Platform: UNKNOWN
